{
  "creds": {
    "noiseKey": {
      "private": {
        "type": "Buffer",
        "data": "6M4bqlpbGEQNHWIiJbwjI91QbSokIVg1oh12M5Fp6WU="
      },
      "public": {
        "type": "Buffer",
        "data": "ogktq4w1PL4C2qULjwIXAbHgrIj2ZHefvfeNsrgsugY="
      }
    },
    "signedIdentityKey": {
      "private": {
        "type": "Buffer",
        "data": "6P1uBISNjY37cSMblp3qLctlLnMweoygCE3KwDRi+1o="
      },
      "public": {
        "type": "Buffer",
        "data": "zyd9c+ZuNBjO0yz5QwEHSGu8s8qwZpEW07TSSsPAdCk="
      }
    },
    "signedPreKey": {
      "keyPair": {
        "private": {
          "type": "Buffer",
          "data": "sJ30sPZ8Oe++kWaDk3n4BostRMQKNWJ8O8mD0pyLO3g="
        },
        "public": {
          "type": "Buffer",
          "data": "RwYU1QV11yiG0dUr+PCzFMIi1RpCni8+RXn8OAtQLVg="
        }
      },
      "signature": {
        "type": "Buffer",
        "data": "c2Cb+EwBTMu9bpXiZ39hFHo1yNidwCXF47Xz/hPZA8Q0UAf4LpQoyfQhih1EEfjjgwylJpktl9WO2ZxQyZ8+hw=="
      },
      "keyId": 1
    },
    "registrationId": 206,
    "advSecretKey": "x4I8hK/+PnitwYus+U8ZSpy2hvDhuNVXdfjSmHhYOpM=",
    "processedHistoryMessages": [
      {
        "key": {
          "remoteJid": "6283874607277@s.whatsapp.net",
          "fromMe": true,
          "id": "78236378437966F6865DC5078CFDBFB2"
        },
        "messageTimestamp": 1661773812
      },
      {
        "key": {
          "remoteJid": "6283874607277@s.whatsapp.net",
          "fromMe": true,
          "id": "E9EA24A8051A64EBD789ADEA8385348E"
        },
        "messageTimestamp": 1661773812
      },
      {
        "key": {
          "remoteJid": "6283874607277@s.whatsapp.net",
          "fromMe": true,
          "id": "A46708867850BEED0CC21D85D9E306DD"
        },
        "messageTimestamp": 1661773829
      }
    ],
    "nextPreKeyId": 31,
    "firstUnuploadedPreKeyId": 31,
    "accountSettings": {
      "unarchiveChats": false
    },
    "account": {
      "details": "CP6pi7IDEOzPspgGGAE=",
      "accountSignatureKey": "19RiH3iFsF7/708V3cryL+V6w1JysTF7Gl7+fKmGoW0=",
      "accountSignature": "SdvJrxlJguzmXrisnZX00CoSe7qOgGcUv3HiLbn5bqa0fZuotOt9nrSKlgaVvZoC/nxD6b6hvH1O27HzE54xCg==",
      "deviceSignature": "gv7fWJ3EyWaM8+1HtwIe21MOiYiboBiX99IEXugNlvSmYy6FiQYQeUjvMKRIsNZmestwtwIEkVk/bKcfA+sgjg=="
    },
    "me": {
      "id": "6283874607277:2@s.whatsapp.net",
      "name": "Meldaa"
    },
    "signalIdentities": [
      {
        "identifier": {
          "name": "6283874607277:2@s.whatsapp.net",
          "deviceId": 0
        },
        "identifierKey": {
          "type": "Buffer",
          "data": "BdfUYh94hbBe/+9PFd3K8i/lesNScrExexpe/nyphqFt"
        }
      }
    ],
    "platform": "smba",
    "lastAccountSyncTimestamp": 1661773810,
    "myAppStateKeyId": "AAAAAF5P"
  },
  "keys": {
    "preKeys": {
      "1": {
        "private": {
          "type": "Buffer",
          "data": "kETHtOrJOZedhCRN+NppdKJggiaezTN2LZNlY22nTmc="
        },
        "public": {
          "type": "Buffer",
          "data": "i7S1jQDDYPX0k7iTh58qagNd+MZhAzfAb9J1lBBk9Fk="
        }
      },
      "2": {
        "private": {
          "type": "Buffer",
          "data": "aF7f6l9ofZ+Xx1ioWQQeFxJSyHORv5AuQ43xyWpxbm0="
        },
        "public": {
          "type": "Buffer",
          "data": "KZ9K7bZgsCG2rBvH1gCFSqEPR39lSTc5AtDznQ05mFQ="
        }
      },
      "3": {
        "private": {
          "type": "Buffer",
          "data": "6AWjsYQdoCYPyfUBRXV62PNYpEy641lLcSqpTdgq3Gc="
        },
        "public": {
          "type": "Buffer",
          "data": "+Pqt9/fISIlDSN+Y3ZO7LJ0xDV+sgia3WC/Jhp0VsDE="
        }
      },
      "4": {
        "private": {
          "type": "Buffer",
          "data": "+M53+ib6mLB22gfWmrYHbEng8MEL32HkFLLPkrcqC2U="
        },
        "public": {
          "type": "Buffer",
          "data": "fyLESUjIwrA/ny4TbAl6OW1e7G1FpQSzHeZzxKuGY3g="
        }
      },
      "5": {
        "private": {
          "type": "Buffer",
          "data": "4J59C+9jHeoIxnhAAV/Riyo6cYJMvUL6HiSEXyQLtng="
        },
        "public": {
          "type": "Buffer",
          "data": "x9v9tPLDyjGoHpZTF634QmqyXs4uy8gZb1gRbW6ofiU="
        }
      },
      "6": null,
      "7": {
        "private": {
          "type": "Buffer",
          "data": "sL3RHc2TLBbeA20R+s0QXwWnE51nYhcUBpEBv5zAAU0="
        },
        "public": {
          "type": "Buffer",
          "data": "IlYmgwJMFr1npi3F54QoOuM5LM470fJIVT8qh7ERYEQ="
        }
      },
      "8": null,
      "9": {
        "private": {
          "type": "Buffer",
          "data": "oHtGKzWdPYzg37New9cIUiOFbTvV0yRDwv+R/YPjw2I="
        },
        "public": {
          "type": "Buffer",
          "data": "qi3YgMwDggPI5qOKAHUKEo9AZDzsMcmabRE1WtHcQRg="
        }
      },
      "10": {
        "private": {
          "type": "Buffer",
          "data": "4CU/9JEjEt05CNQ7qvfx9AsgwPtGSTAzPngFSfBKA34="
        },
        "public": {
          "type": "Buffer",
          "data": "O0iSdxqgqT7kPzleiL7RF7t/1E4t5xC1FVCha54D1AM="
        }
      },
      "11": {
        "private": {
          "type": "Buffer",
          "data": "IL7yf3XvQ2x5j+M5gvWzg/VFlPIBrL68MJY9SexjhUA="
        },
        "public": {
          "type": "Buffer",
          "data": "kHG/tievRv90ymZnm+KiqSFKP+Gbj6b4VPVixbAlLF0="
        }
      },
      "12": {
        "private": {
          "type": "Buffer",
          "data": "MFe+F20TIAauh+rAmDPf2R/V+gEW8EWN7EO9fg6aHnU="
        },
        "public": {
          "type": "Buffer",
          "data": "83tUUlen4rClPRSaX30yfkY0JlPp/HdIkh3rx9CKUUs="
        }
      },
      "13": {
        "private": {
          "type": "Buffer",
          "data": "AOa/FPFGDoZijYDNv+EY5Cc0DqNLp7F4OV/O/WJ7UEk="
        },
        "public": {
          "type": "Buffer",
          "data": "NgQvKr2JagZ6NzV2KcPoldpz4Kat6f+3j5o/q92FNnc="
        }
      },
      "14": {
        "private": {
          "type": "Buffer",
          "data": "YAeQ2rfp9KqCQ2otlI2jdrIHpMzS5EF3fYMiVQz962s="
        },
        "public": {
          "type": "Buffer",
          "data": "bydrPhBY08zoJqB5/gLlSyajmxyk3LZzeA0MEJe2Dkg="
        }
      },
      "15": {
        "private": {
          "type": "Buffer",
          "data": "ONe0bEykIaNvy5oX+T1nbaptRCAcSx0Ap5SwHNfIs3I="
        },
        "public": {
          "type": "Buffer",
          "data": "se9u4H7LSnqi3bmq/1oW1Bgt2ZbJsY1VJ1cpPXJf5Dw="
        }
      },
      "16": {
        "private": {
          "type": "Buffer",
          "data": "uDzU542sqzOHTZ9h98LyBUx24Py2Ofh5mfAen2cD5VY="
        },
        "public": {
          "type": "Buffer",
          "data": "xxC6Km3Y5SR4UYtjy9URZSjmeWxhJ4rRKY9TX//IXk4="
        }
      },
      "17": {
        "private": {
          "type": "Buffer",
          "data": "sJYPeSFkfPtOqmPsyuhORWm1fKXXoIOvg5hkNrjlw2w="
        },
        "public": {
          "type": "Buffer",
          "data": "gv+oP+ExPDIjmZ7cXMTpf51CnZMuE2zCKGZ/Z5bxQXM="
        }
      },
      "18": {
        "private": {
          "type": "Buffer",
          "data": "yHAYC031+pOJKCUHW48SF2XVpLpy6hNFcwXckkXg4Gk="
        },
        "public": {
          "type": "Buffer",
          "data": "hFLsDLjMVRmOWcaAtwtnJm0DtSaVXLieNV/MQBfDuHQ="
        }
      },
      "19": {
        "private": {
          "type": "Buffer",
          "data": "GDdp8wWEa0W2N60J/MBtyvKD7jULsdAZKi5CcaujuV0="
        },
        "public": {
          "type": "Buffer",
          "data": "Lw0uClH/ZHI9mOBwcm6cticY4et63ahlgufqI1yOU3o="
        }
      },
      "20": null,
      "21": {
        "private": {
          "type": "Buffer",
          "data": "MGUornih/Yr12N8t5ibDcRfwX8Rb7WSRthZcZkK8+1o="
        },
        "public": {
          "type": "Buffer",
          "data": "7Nwftj+Mk/jAr9Z4zQNh/tjyDET8/+qCnwZMo5elVUs="
        }
      },
      "22": {
        "private": {
          "type": "Buffer",
          "data": "qIiV2CuZtE/stB+fidXQjH9S9n8Cl8EIxUa5UdNTSGw="
        },
        "public": {
          "type": "Buffer",
          "data": "KlCOuvuJrU5+qXoe3Gjeh6TGHAYG6+7tcz5MknDlXXE="
        }
      },
      "23": {
        "private": {
          "type": "Buffer",
          "data": "8CW+n9GOt57E6dzhGKILR+V7/QMOSZhBXovwr0fv/U8="
        },
        "public": {
          "type": "Buffer",
          "data": "fAnDGYxrCy46POxTH25BKSlCsnOZis3xhU1dHmvRlUA="
        }
      },
      "24": {
        "private": {
          "type": "Buffer",
          "data": "SNN57Yvul6/5Ky6UNQT5G8o74LFu1fYK/uz/1lJfumc="
        },
        "public": {
          "type": "Buffer",
          "data": "PGNgoiPOyJ8cUua4HQ3KNhM0GoTDeKJrLMy8Ngs0ix8="
        }
      },
      "25": {
        "private": {
          "type": "Buffer",
          "data": "8KNkjIo83w+WVmRKcfpc29jCWDArJplFJslls7tmt3g="
        },
        "public": {
          "type": "Buffer",
          "data": "cNgRZhKMZ4Zzb/iBJeXOPpWViryUa/cgAYmILhVUKzg="
        }
      },
      "26": {
        "private": {
          "type": "Buffer",
          "data": "CAMn1OLMdcywT7akoi75fyaZWIE+fn675c5wNvPTj1g="
        },
        "public": {
          "type": "Buffer",
          "data": "5zpDIKj43Djdav2VYP/1Pz72jLcWOKYt8duwkSngkhE="
        }
      },
      "27": {
        "private": {
          "type": "Buffer",
          "data": "+MoXqpx2zRuWzGXLGzjOvWsXoCDs+PSmbfopqVea3X4="
        },
        "public": {
          "type": "Buffer",
          "data": "Ywda8zQwny78HCa6JNppUxbJB/FZ9bHTkgAu4Dk1wD4="
        }
      },
      "28": {
        "private": {
          "type": "Buffer",
          "data": "6CiUKqWZ1L44WxCxr5sRkrAia7DC2Fx8JKOCQiqUI3s="
        },
        "public": {
          "type": "Buffer",
          "data": "2wuhWq7lWqaThJT9Jvks27x3WiRenlsYN8pnimQuCis="
        }
      },
      "29": {
        "private": {
          "type": "Buffer",
          "data": "EFkD7/Nlt8u6OpP+/GWEA0i6Awxh2delKsEcfu0seGQ="
        },
        "public": {
          "type": "Buffer",
          "data": "RHzF7dg7SPYJcctKLzfQ1RWi1J6/v/p8XJ5HZ8eApBM="
        }
      },
      "30": {
        "private": {
          "type": "Buffer",
          "data": "ePYKd/afyU1mWST4c+YBLk1BduL9XBjWK3Ib2iJFNHQ="
        },
        "public": {
          "type": "Buffer",
          "data": "BnPBrN1FbrDdi5YHNTlBA+m+Q42/mZsh/c5/IaTIokg="
        }
      }
    },
    "sessions": {
      "6283874607277.0": {
        "_sessions": {
          "BWVTaqwyV+vwn9LYIu/o3xcdozVhHIG+uE1aa+DH6mUx": {
            "registrationId": 1629897575,
            "currentRatchet": {
              "ephemeralKeyPair": {
                "pubKey": "BR79dl/FxR6BhSSz8Lk+WJYDRmRvEIUprFdI43TyDdQO",
                "privKey": "mDpKQj8tZuGztXEHcfiwmvNIsFepiugpR8rFZ46s5FA="
              },
              "lastRemoteEphemeralKey": "BVMN3ebvIecvTakM5ptEKpMrMymOmzWQHxv741sNINYj",
              "previousCounter": 0,
              "rootKey": "hrHazE+67QVmFi7oj8ewmyw5cirmwvSe2dr4qErJKLw="
            },
            "indexInfo": {
              "baseKey": "BWVTaqwyV+vwn9LYIu/o3xcdozVhHIG+uE1aa+DH6mUx",
              "baseKeyType": 2,
              "closed": -1,
              "used": 1661773812088,
              "created": 1661773812088,
              "remoteIdentityKey": "BdfUYh94hbBe/+9PFd3K8i/lesNScrExexpe/nyphqFt"
            },
            "_chains": {
              "BVMN3ebvIecvTakM5ptEKpMrMymOmzWQHxv741sNINYj": {
                "chainKey": {
                  "counter": 6,
                  "key": "CNlv9Hp5KB1zMbycIKGL/7oUTaC5/qz3trwdpYyypdQ="
                },
                "chainType": 2,
                "messageKeys": {}
              },
              "BR79dl/FxR6BhSSz8Lk+WJYDRmRvEIUprFdI43TyDdQO": {
                "chainKey": {
                  "counter": 1,
                  "key": "2kgQ5O/kS2sOevIWpN9cEYIfAmzE13Aesiqwz/3GxHM="
                },
                "chainType": 1,
                "messageKeys": {}
              }
            }
          }
        },
        "version": "v1"
      },
      "6285783926465.0": {
        "_sessions": {
          "BYL1l2a/geSXhVoso9zh2IwZNzd06KELsKUfe1poEawu": {
            "registrationId": 1333719862,
            "currentRatchet": {
              "ephemeralKeyPair": {
                "pubKey": "BWRFh+yDReP+gwXs1d0OP/lVLVl3P0z7UtoiN15CzrUT",
                "privKey": "SEVgRjV/3YcKtDGEejIckjpn+K6cqGGHY8sjkqa+HE4="
              },
              "lastRemoteEphemeralKey": "BZli/j17MXrYVan4u3KjodTrNYK4mi9naOCIHoyXfk06",
              "previousCounter": 0,
              "rootKey": "Snfd9YQoIeG0YDta6hM/N6tKZv0EOjcufacnSY2co+Y="
            },
            "indexInfo": {
              "baseKey": "BYL1l2a/geSXhVoso9zh2IwZNzd06KELsKUfe1poEawu",
              "baseKeyType": 2,
              "closed": -1,
              "used": 1661773846971,
              "created": 1661773846971,
              "remoteIdentityKey": "BcPozGNdtST2zCxpoC0K8uN1Uos1SOpohXXnlssiM90x"
            },
            "_chains": {
              "BZli/j17MXrYVan4u3KjodTrNYK4mi9naOCIHoyXfk06": {
                "chainKey": {
                  "counter": 0,
                  "key": "oXcihqeoPcTpi+8doJXWjpP1oDHVIICms4qFJAD7Tf0="
                },
                "chainType": 2,
                "messageKeys": {}
              },
              "BWRFh+yDReP+gwXs1d0OP/lVLVl3P0z7UtoiN15CzrUT": {
                "chainKey": {
                  "counter": -1,
                  "key": "8Cbdxh1sXvhGgogCPtSf9uRufrjVLnnePHRdQxujjKk="
                },
                "chainType": 1,
                "messageKeys": {}
              }
            }
          }
        },
        "version": "v1"
      },
      "6281214281312:28.0": {
        "_sessions": {
          "BTotwIIzDrkOC5gCTpLAL/N/morm/GkbFUrkl0uVXGcT": {
            "registrationId": 205,
            "currentRatchet": {
              "ephemeralKeyPair": {
                "pubKey": "BeeAHNq0k9e0OvqY2C7h8obzqmJzy/djYH7i6eZEt+cF",
                "privKey": "OJw1RHMM29p9PIEFvuEV1Kl/DoPPVbF/hoOagfaG9lI="
              },
              "lastRemoteEphemeralKey": "BZA+cO/QTxBlX9BdX54fRJjikLj6dUAVxFSF5ZN4MqpI",
              "previousCounter": 0,
              "rootKey": "6ITc9K0S+0+EHuak0rKJ3xSiTiIi7S0gNrDfwk8DEN4="
            },
            "indexInfo": {
              "baseKey": "BTotwIIzDrkOC5gCTpLAL/N/morm/GkbFUrkl0uVXGcT",
              "baseKeyType": 2,
              "closed": -1,
              "used": 1661773861838,
              "created": 1661773861838,
              "remoteIdentityKey": "BZPO1LpbBBsG49IzaCgMm+sd2CnWn1oNtb7AJJa9s2Nd"
            },
            "_chains": {
              "BZA+cO/QTxBlX9BdX54fRJjikLj6dUAVxFSF5ZN4MqpI": {
                "chainKey": {
                  "counter": 2,
                  "key": "fLG8mSmu54YIhZNnJ7zwa2xViAKTzi3/RXlInHSyadc="
                },
                "chainType": 2,
                "messageKeys": {}
              },
              "BeeAHNq0k9e0OvqY2C7h8obzqmJzy/djYH7i6eZEt+cF": {
                "chainKey": {
                  "counter": -1,
                  "key": "OF7mwGLdKKv8217xg1zjBlSCXB1orSwqkdIodhqGtLs="
                },
                "chainType": 1,
                "messageKeys": {}
              }
            }
          }
        },
        "version": "v1"
      },
      "6288223674569.0": {
        "_sessions": {
          "BUjpWeZn5RVOXVFG2R/sj2tvghsK23llLTNM57Y4uEtq": {
            "registrationId": 380623093,
            "currentRatchet": {
              "ephemeralKeyPair": {
                "pubKey": "BbHrXzardfibs2FOXFQnhb1XC7lTAG9MRRV0d8wGrCV5",
                "privKey": "QLvl/iCWrep/U+ua0uKz8TVzyxl3s7YDeZtp2IY/8Fo="
              },
              "lastRemoteEphemeralKey": "BV3YQyhpSfMvYqFbL6ARKTAfHVRnpbBQ+JzFL5vpwRdn",
              "previousCounter": 0,
              "rootKey": "ZCvrrFparky9m+ELFponHEc+DWtS5B91EojU5Bdc8RU="
            },
            "indexInfo": {
              "baseKey": "BUjpWeZn5RVOXVFG2R/sj2tvghsK23llLTNM57Y4uEtq",
              "baseKeyType": 2,
              "closed": -1,
              "used": 1661773891062,
              "created": 1661773891062,
              "remoteIdentityKey": "BW/gmBq6gFcqhORdrJ6Q6UynURr4QjjZP100DBQEWpMc"
            },
            "_chains": {
              "BV3YQyhpSfMvYqFbL6ARKTAfHVRnpbBQ+JzFL5vpwRdn": {
                "chainKey": {
                  "counter": 0,
                  "key": "FvKgDLEnodYY9SIJD8I+9pEp6dQvQOJdSrmweZJUiZo="
                },
                "chainType": 2,
                "messageKeys": {}
              },
              "BbHrXzardfibs2FOXFQnhb1XC7lTAG9MRRV0d8wGrCV5": {
                "chainKey": {
                  "counter": 1,
                  "key": "Hb02m0rH4mkKlUc5RoIgAKfz5qh93H9yMT9IZ72yvJM="
                },
                "chainType": 1,
                "messageKeys": {}
              }
            }
          }
        },
        "version": "v1"
      }
    },
    "appStateSyncKeys": {
      "AAAAAF5P": {
        "keyData": "7JDejEzGf51iOQUbSMWOUqXDRX+QLVqg3SArwHp9mQc=",
        "fingerprint": {
          "rawId": 910349566,
          "currentIndex": 1,
          "deviceIndexes": [
            0,
            1
          ]
        },
        "timestamp": "1661773811352"
      }
    },
    "appStateVersions": {
      "critical_block": {
        "version": 1,
        "hash": {
          "type": "Buffer",
          "data": "n1OCVmVx1MFSUeBNPtm+TUmUH4WsbCN0yMrq5ZkNAKR1yiDDHSpsy4km78MdLzxfiFtwZuhr0d6o8eJStcBlwYgod5fSwlVwWDRlddeH/Q5Azz7FuDanVYKoUckID7VyhG8O32RtVungwZmsJAy+fiaMAiRhhskbD5sdSrfbn+8="
        },
        "indexValueMap": {
          "CTqZp6yrDgNlt7YctqQOYI8FsToG+F0O4gUFzr2r78k=": {
            "valueMac": {
              "type": "Buffer",
              "data": "HWqznNS1nOZIdb6p8b/Eds78A+LqKI5pL/FHom4lB7Y="
            }
          },
          "zwyPhqHpAohuhLx2NxUbBMGvtTyD3DZ6Cl9tCdhut3g=": {
            "valueMac": {
              "type": "Buffer",
              "data": "dOVc8ZrX23kNUhSjwmm4VO1Py5nGa0reShBcc3Oia1Y="
            }
          }
        }
      },
      "regular": {
        "version": 1,
        "hash": {
          "type": "Buffer",
          "data": "DZSAIqNpOy0fBEDdcNzcw+Yu+aTUsYGcg2Zza47WODBvffLJiFZCQqtTwyL+wmhiRmwtCUB0BoBWssA5xrGr0cGpHedPozo+LZKFEr0Fkmv93jTBwvyGB4y1OiEYBBI3cYH1wOjI9Pnt65o48rcSBkfABTRNBgBY9ie5H6z7DYk="
        },
        "indexValueMap": {
          "185cOmb0VWcghgoqSun5jLvBkcSMLjpkFH+RZnc9Qiw=": {
            "valueMac": {
              "type": "Buffer",
              "data": "/njKybbN0lHZnepLsRTmO46PEqa/RMITRGClrnv0Mf8="
            }
          },
          "cUSmIeFDiyeBfO4wJXoceIVP4zsxrGsVI+kwoQCaEKM=": {
            "valueMac": {
              "type": "Buffer",
              "data": "cd1uXTfPEjMvaV7tmCt26iklf7CTvzqV+Y4xCyQe6DA="
            }
          },
          "HKXqQBtpQEGrXjjXtkBZfCOB/Jtgrb7z7XPSOdO8te4=": {
            "valueMac": {
              "type": "Buffer",
              "data": "ppKPk8EnkqIViXLvyW0Btu6P96/JGJUPdOXpenIKTxQ="
            }
          },
          "AmcBQwkkmPUmdh000mWQ3lTh4zB3cT5C0pOZ7DYuLk0=": {
            "valueMac": {
              "type": "Buffer",
              "data": "j9APhiiOShjfLxRZAKYMNONqk1gsp3lLUV34KqvO+no="
            }
          },
          "2XQzbySd8BEVd22mCbTLU14UFvIqCT9yXGcIULC/AJI=": {
            "valueMac": {
              "type": "Buffer",
              "data": "nn+A0LG2ItA2o2I7Bbv8ToFXLn/i2vrt8vjDOU+dWIQ="
            }
          },
          "N84zHAGaDVf2sFzkYsQFyLa0OP52jSCkwBsPu+LEzf0=": {
            "valueMac": {
              "type": "Buffer",
              "data": "0Sd+E/J0am+xOGJtvybR+TQpReFKemo8kVR1/wDolZE="
            }
          }
        }
      },
      "critical_unblock_low": {
        "version": 1,
        "hash": {
          "type": "Buffer",
          "data": "ETSir4MdEmtwOOLuTjkXF7lrlxoXrw3JJynIMIA0uw4SnSf4Ry3e7YBHjilcWXeAXYMn3Bfgl9f0H6XCJrdTgDOAlxSP0NG2dXfNeLCXy+hJaLKlEP4i5i31BEp1raoWBrN1LHcC/kXKd3H/Pdw8jMkQOelIAl6X6sWaUHLAVA0="
        },
        "indexValueMap": {
          "d6QDTftRfIHk+v95tYuW/A29SSvjl4w2Oq8T5Td/kZA=": {
            "valueMac": {
              "type": "Buffer",
              "data": "Fi8g6cxsKfkmJ7T/b9Gv8P763L+dd8THidykI4Lj2qM="
            }
          },
          "P/KXZ+9RNOxIl7qxNAOhwcgbKPySzeIXZhmIBra2mSQ=": {
            "valueMac": {
              "type": "Buffer",
              "data": "0RKDmr7fRHyznoK6j0J5U4lkY+x0fCbC3kLldOwqAnc="
            }
          },
          "gnZWH/x3LwUdV+7IXjklpYDQ5mmyg6zHuNDJqwviRYs=": {
            "valueMac": {
              "type": "Buffer",
              "data": "H5TVbO5OwUE+pUmqTUWn0F19n3jV5tRk/11DKt43W7Y="
            }
          },
          "U2cdaBj9OTZFpeOZs3Tr7SP+t1yHSb2Tpr7B7bC5+rY=": {
            "valueMac": {
              "type": "Buffer",
              "data": "udC6cRw27tpGf2K7eD7TMuS0jRuww5Ta1BMfu3FCFPc="
            }
          },
          "X4ldL7mwxg4jlukd2IREV2/IRi84A4q7BDgk4QdPr1w=": {
            "valueMac": {
              "type": "Buffer",
              "data": "6Gi0r2CTcWURNCwlCLrXcmmyOjVRnYJc9jFY7M91hXE="
            }
          },
          "xq+GF8Lp1Z8VaEmowM2OkjZOsgPuuxmvd5+219ZumBI=": {
            "valueMac": {
              "type": "Buffer",
              "data": "mIQxyIjTiCvW++wiZwgv3N7EGyFtS8s0SvxvbW+9ALE="
            }
          },
          "8sSLmehPKDZJp3s38NLL78tZrVJvjVoMBkkJDcHhJ/A=": {
            "valueMac": {
              "type": "Buffer",
              "data": "izxMDivVcwZ+GFNtsiv3sqYI0tre2tKkOqkUhVyCpKo="
            }
          },
          "9eBI2ekXrRqplbJcb3Y+PMQUEdadRuWywlKo/wGzdQ4=": {
            "valueMac": {
              "type": "Buffer",
              "data": "axvIr8E+1ycrjW4IcR4NVPghZ264NVum7YWT2V7vRQU="
            }
          },
          "GvAihTR3/bOR7sBcML2on4YnKQcziqSx5fI63XZ2ZXI=": {
            "valueMac": {
              "type": "Buffer",
              "data": "SrGuB/vRU6ptaOKHMhJMMVEvF3vjdB43M11s+zmnhVQ="
            }
          },
          "hHl6oPn0Kc6NZVE6kRUaxK2AVR2Fq94ymExxhH5AoHo=": {
            "valueMac": {
              "type": "Buffer",
              "data": "tIpErr67dA3dQ4/SqQ/D4Ds/Onsq/Sunsys1T06f6S0="
            }
          },
          "61iCRZjCT/g/wP6brdg6wX76eMbLRuGlcWZ+hh0EVlw=": {
            "valueMac": {
              "type": "Buffer",
              "data": "lizPjXPJ4/XLStUhDQSQAy9oVYZuY9m4sRgo9mu4rgI="
            }
          },
          "/VXF1wuNYWCcbWgCsWXubtWcouzwSbh2sHIyTD3hJR0=": {
            "valueMac": {
              "type": "Buffer",
              "data": "KQFlem0erAyC0IRybYyeyEofSELhu/gI1PPdipVQ/0Q="
            }
          },
          "4R68NBZ2YKFh+m0ASXrTYMYYeqRyuoQc82Ha1qwB8kQ=": {
            "valueMac": {
              "type": "Buffer",
              "data": "kZJT/dNJgzdSPvGbjVflKoQvgXS43gXMGZoxX31kDDE="
            }
          },
          "A80sWKZ0Tv1deN7eg3MSAD5NkgKdcSKl54V5fMs/rog=": {
            "valueMac": {
              "type": "Buffer",
              "data": "ATpDgotVIt3o/jSuNOr/c0tShexYq1io8osHh5ERRjw="
            }
          },
          "bYTVEuX/WAwwG7EYJ+C5o7wVQ9tsBiPHlJdRw4fAtl4=": {
            "valueMac": {
              "type": "Buffer",
              "data": "QNgaiZlE3rhznekF4s/glwZ7FvqnCU1xhw0JuLbe65Y="
            }
          },
          "zXPwqkk+kOynPIEdcrNhnb41MtdQRm6MIB5VzqTJ3xA=": {
            "valueMac": {
              "type": "Buffer",
              "data": "Vi6/DujqHV9vpXznYz98XU5oCfBnNkq47O49LPIuAQE="
            }
          },
          "GxVxesxYUM8f+p3ODkYaI6h65TiaZklFr5r/PcdK93Q=": {
            "valueMac": {
              "type": "Buffer",
              "data": "A08dtofyN/3q5iK7BBZKZ1TdA+RvUrLigBp4q132zn0="
            }
          },
          "gNN1nuDq92AUfRGk/OPPJaXJnKfQn+pU122gGshOy2Y=": {
            "valueMac": {
              "type": "Buffer",
              "data": "Is83u7f1wXUHmGCBhH9faj3rlISUiMtRcDtLQ7pZsjk="
            }
          },
          "dkgA6wgSwJgwWWhq5T9+a31ZuWDXUZAzUTLz3eYvngQ=": {
            "valueMac": {
              "type": "Buffer",
              "data": "EW+ySJL+yi5mgjmR6v0Lm1THdqTaKFIW6aFqiCO3nM4="
            }
          },
          "f/w+/Tesbol0rp6ETPpaVHe42rmQO5JG1xnlZ8Gah9Q=": {
            "valueMac": {
              "type": "Buffer",
              "data": "VBVtyED3IKBELwUFFbyAocgwzdG9EmFi/d9A16WhC6Q="
            }
          },
          "1LAVrCSG/Rzs2qorS5NYqFZiK+vz/6uFqA6aC492/VU=": {
            "valueMac": {
              "type": "Buffer",
              "data": "4fHi0/zwVvqF0EnYIDBBPkXeUKsMjVAYcWCYc14iX+Q="
            }
          },
          "RNnu3235qRLJaubxvFmILTzgAt8CFh1+ST2KuFjjpYA=": {
            "valueMac": {
              "type": "Buffer",
              "data": "9Q4QAEFUZhYCLpdjbexhBsCzJ2QyYDpPyQ+Xj+nIZYQ="
            }
          },
          "yWHmnkkLGP24tqojxI/+5EahxkThZiKpP4GoJtVF2VI=": {
            "valueMac": {
              "type": "Buffer",
              "data": "t9dSN+HTOdZOBKXzGkRQRlktD+wg5eSaQcaGdsvYfFc="
            }
          },
          "iIzo23aHr9uvbuMug8kISbCPH+LAkKWVau8kQv9vtnY=": {
            "valueMac": {
              "type": "Buffer",
              "data": "8gmZK7fkfr4MCIoNM/beA6HBxt4w/DN1CeiAd0N7aw8="
            }
          },
          "VIAsqCsK3vNsniGJB6t+mqfwB9C+wRUmF7CMxxpBTV4=": {
            "valueMac": {
              "type": "Buffer",
              "data": "ExQ1469Y1cgJpOpJFuuzXssVRVO/xsE7FlDZHYgHFoA="
            }
          },
          "r90W6/mvFRmq2XAZMGlANAoeSrYUTjIcHMg8D2IEHII=": {
            "valueMac": {
              "type": "Buffer",
              "data": "ewPdIVv8MMBOafrICFE0AvAewQ9wCJ9weh1Fb2qWa5w="
            }
          },
          "RSFLs6R3yx5Ped/xCR5YGZ+pOnNnqR5UE5yZrdld6Bw=": {
            "valueMac": {
              "type": "Buffer",
              "data": "3OUMhtmRo3e7TbVGQboBBMXhD8DX1yThlxeO1gLbnDQ="
            }
          },
          "7uBIKL4rvpaEKzTc/CEJbcze+WttCJGJCQxuNJuNWuo=": {
            "valueMac": {
              "type": "Buffer",
              "data": "qBiIPI9lAE0jlMPX2MoYJH5BTint/r/gQThcmXw628U="
            }
          },
          "1rgRAhLbg4JZ3DcMpsEV9FVbr3tBwB/qeBweIP2R2i4=": {
            "valueMac": {
              "type": "Buffer",
              "data": "5s7UoaiA2TJ9VUtwWCYAkHWPQybAEKCX/8JQlFOoL04="
            }
          },
          "Lxex6hEz9e5eE2SRbdm1XO+7LTnboCiCgvzX6nMZEmA=": {
            "valueMac": {
              "type": "Buffer",
              "data": "1CfhQAQJY8onawetqAPa9vvfPQ8/E3kBm84SeoxIyos="
            }
          },
          "w8lYbIs1eyvHVzoPdqPD3u1VgWDbqvhXsgYhuzRDvXY=": {
            "valueMac": {
              "type": "Buffer",
              "data": "MmeVF4eMuKlebawAtWtdsJvTMFjdTY2pAAYHSGGwwt0="
            }
          },
          "giYP4CusCkC9zjeHkT4L35zKcD9jta1ccSIKoAvKeu4=": {
            "valueMac": {
              "type": "Buffer",
              "data": "TUbkMdawPygEnZ77nNrlLU3soTSNLVsnxMduSfgycVY="
            }
          },
          "JRLS1b1UEUXXLhgzrFdej9KllBG9N8dlcpLcb/9frsc=": {
            "valueMac": {
              "type": "Buffer",
              "data": "T7DpYCluW0NXhjpGuKXN6x3h33dRGSxO/ueFEAkcr1A="
            }
          },
          "rWN83PkuZmVTRrxOpy/rp2OdJybByhnH2gRLcfCsOjA=": {
            "valueMac": {
              "type": "Buffer",
              "data": "wPKwJIpr265wnd1WGnreQc4JCIrjZuF6LbcN2wSXa+E="
            }
          },
          "4kXRhQaPH5Wlpv2UCb6dZNR8wnfeNfJ62yakxnDguhM=": {
            "valueMac": {
              "type": "Buffer",
              "data": "d5gBSUxPUeqqX10dgCRFd83Ux3onDVKbyT3bIzCeKHM="
            }
          },
          "CoJgGHWfWYuA8TnvvsOI640KK+CGoH9jPNPJNz0g62A=": {
            "valueMac": {
              "type": "Buffer",
              "data": "Ck4dteNT3/7eBCa3Iebr6KxnkyghAzI2FT+V9wtyBVg="
            }
          },
          "hOfS56H36ar52+B64Fgb7/uvP3diBmAQIRYnrpfr3Ms=": {
            "valueMac": {
              "type": "Buffer",
              "data": "ETVxZ0HEkYC5PFgoW8BkPd97HX+nilScqluUWprMYMw="
            }
          },
          "g0VIKz5m1h/Q8mHDUbDyoL4/qyDblxMPtNwqr2qS3d4=": {
            "valueMac": {
              "type": "Buffer",
              "data": "gDPuk5myBeGmbhPedS00uT39Nc/NGIqExGpKE41UwZA="
            }
          },
          "4Ul5iY9dGI7nqPZoOsgRrmDzHUPm0jyAlxYaaDiSUrI=": {
            "valueMac": {
              "type": "Buffer",
              "data": "4dqTXcSWo7GXf2tffnSoB4S6fOmG00M71mVMGkMdezw="
            }
          },
          "VJXWwN8THjDHpj5bR5OJSFXUxTOVsAh+dSTH2qI5WCU=": {
            "valueMac": {
              "type": "Buffer",
              "data": "1innbG0rAXpImQPU2CDuyF8e4XHxxumY5YB8bwkCfG8="
            }
          },
          "CgvF/q+80s1v2K7uVoEpQjuRDJ7znNXt/24z3bD2DDs=": {
            "valueMac": {
              "type": "Buffer",
              "data": "OJXL/Gfy080YdyfqvleT/oZRqed3IKQNKkpLV1DrQPk="
            }
          },
          "ZLAqzNE+dx7eApyzLse8Ano78zzmO4iBVishJbx98tQ=": {
            "valueMac": {
              "type": "Buffer",
              "data": "5T9AaEs82Nt2VByo1SY/caJ1CTpfCqsbwd3cy6MhXi8="
            }
          },
          "xtshlMQ2iBZNZTFSlrPEQU9jqu15TR7FN0YdWcazNxY=": {
            "valueMac": {
              "type": "Buffer",
              "data": "ckmxudx2pRz9hntx//w9DoTl8e7b06xBRVs7uSWjNRk="
            }
          },
          "fESWiOq/QFdFA90BfrShAI/iIg+S1b1KNAsytuDBcmA=": {
            "valueMac": {
              "type": "Buffer",
              "data": "ZsRQR/m6MEVjepJUJIYzB8USA6U4D2mJZNglx5Wdg7A="
            }
          },
          "utc49HEHVuqcAsPDXYwixAuDJ/boOBGScm+cgEvYiYc=": {
            "valueMac": {
              "type": "Buffer",
              "data": "k9G3dg4/iKzHIZz3EPFfsAhq23UzWpQmulKUkjXa8/w="
            }
          },
          "jRj9ECKM93r+DrTrMXzSFovpoGbM4wgjOwQ1kc0JGdo=": {
            "valueMac": {
              "type": "Buffer",
              "data": "wXozW5pao5YzPK0KX2Dmpx7IuKe/ClU/sGS5L5iSgLA="
            }
          },
          "rFY3Umi+54oaKdpoKhrwTMFQbZFtdL2Wtsaxg7X8aRI=": {
            "valueMac": {
              "type": "Buffer",
              "data": "IiDHkTW0ivbZoe0lz0nd6wP0VbEM5vtE91pCWOByvqc="
            }
          },
          "/9hQK99ROel7uEakpld7jOwuZFrM2SYiFRiFJ7LIggg=": {
            "valueMac": {
              "type": "Buffer",
              "data": "0uwkh/6GET+AKN5q2iHXHkTEIqIWbdIbtMT6nOCLJ2s="
            }
          },
          "mv+4OkxnPruCFzpp/3bjf0Jfz6c7XgT7+LX3Q+sZ374=": {
            "valueMac": {
              "type": "Buffer",
              "data": "JF4Pf2gg4Dg3sdaxLgAgRjOq8JImh6uLB5HL/Ir7eOc="
            }
          },
          "sNAAZX+P479zIs0yiOfWLH/DPWz8zKHSHD4tUJTfkCI=": {
            "valueMac": {
              "type": "Buffer",
              "data": "Ft4IlfcAXqxsFowpdyZsjycP6kz1jdlz8fjOnrzNvpU="
            }
          },
          "dzMGM6YKwdt+JmjXeZdswu7qpfD3Yq8wIpLTFYhQ0rg=": {
            "valueMac": {
              "type": "Buffer",
              "data": "+IXD1pjLd6feR2SkJ9NBJRXj69GS/xi4He5MmdYk0ZU="
            }
          },
          "Pt9dy2yn8AsARuBJ8CqSisrkGSWO8RMjYGZrIunsKaY=": {
            "valueMac": {
              "type": "Buffer",
              "data": "cWxT8Ct8DKBoNDpyexl+sCxdhb004sgg0G+/3NBXjOg="
            }
          },
          "1bto186X76jraWMI4wcusPefHM+q67JtRtjcezPOfi4=": {
            "valueMac": {
              "type": "Buffer",
              "data": "aNMk4Ajotu0DTdgdiAudk0xrzyRJ6qBKmifZ7GGv3ps="
            }
          },
          "VHxErp1i506p12qN3qpx8WbRmKew4sbPE26HRFtAoqo=": {
            "valueMac": {
              "type": "Buffer",
              "data": "g2oQOtJb9i+gD3X7VL6WzW9ag1syT578qYU1/Ec1Htc="
            }
          },
          "4YazI6zNkgfT/PG0Hie70IgSH4ZpXxuYHpHcTlOwpRk=": {
            "valueMac": {
              "type": "Buffer",
              "data": "83mIH52V+iE/IFMTur9Svg9Mc2XpBvvQRKuSNACl2Ps="
            }
          },
          "OQZDwWUk/cll2oI4XnT1cGkaynSlUscVBhXs6kA5W3s=": {
            "valueMac": {
              "type": "Buffer",
              "data": "9gvDUShVrqkdWVv3IAo13D9euWnxZqSencZoYJBrrrM="
            }
          },
          "yMoAAGDVoB9OIfe/8cHryo0NRfFtzggBb/2cZ7Wq20A=": {
            "valueMac": {
              "type": "Buffer",
              "data": "3rPSN0LEDS4iSrdW9LEYmvWCBnEIYfqFh+2OtpnyKSE="
            }
          },
          "n2OCAAMsfci7snhBxhxA7qn9gZXCaYFtzVyc6dsWiE4=": {
            "valueMac": {
              "type": "Buffer",
              "data": "aqr4kutznF0yeZanLXlYten2mZsXAl1hulIHSllCmh4="
            }
          },
          "1hk3Kb+WmHRgHODYfBPjhoImPWeO0b+wdNLzMgsSzD8=": {
            "valueMac": {
              "type": "Buffer",
              "data": "2F4pjavkJtywNtm+tfkLq9QCUspI252jJaJELDpd3uk="
            }
          },
          "uNvz1i/6FVclru8+u/Izha4v05gZPYAIwt0y5/obwaQ=": {
            "valueMac": {
              "type": "Buffer",
              "data": "kCsQ4mtciA07eWzrlxTvNLCWUsOYTnyts3vEC6kgmu8="
            }
          },
          "Xu1SxuY2IvpfS3gWGD1NkoZbOfweBJdnNepQik93A/A=": {
            "valueMac": {
              "type": "Buffer",
              "data": "KEHaNh5Eaq20wfF4gQYt8fOKIP+6FVhCTwsCNvaN9iU="
            }
          },
          "QbvMYXW5eMhwg2UkE2imt1UB2dIYtxkuYSs3RgrcjEg=": {
            "valueMac": {
              "type": "Buffer",
              "data": "a8bt9Hc3+tH7YM9QH+X4Bx4k1eDK8wJCHSWQZUA1Tkk="
            }
          },
          "3ViZWLaFzeo/X1RKNmH3NU6dl4720Evc9KyNVCL3XVE=": {
            "valueMac": {
              "type": "Buffer",
              "data": "QkvFnIVJH+SSB9t+eRdWDf8pr1Jy9kac52JNvAceJDc="
            }
          },
          "Ca/uCSXnEKK986AUNCFE1MrZFlOP52AYy/ZEmYaT41M=": {
            "valueMac": {
              "type": "Buffer",
              "data": "xqi6JApKqjcb4LwiM5gyQaUTul0DWg163nAcudlHM5w="
            }
          },
          "RLCV9KBB6PSnbBgsNhPmVTDDeyb6Rdwk28U3uCyX0a0=": {
            "valueMac": {
              "type": "Buffer",
              "data": "Ffd3DI0D07PCi9H+Z7LrS7/EAKLA1DVZJQPByZBlkCw="
            }
          },
          "J2MoYczPw1dL6AenBv6DAw+fL34+eEFv3aFntvc0+P8=": {
            "valueMac": {
              "type": "Buffer",
              "data": "EAOm52zewWC5n1GQRoeFCp3/o6/tWvOZ/sJXxWVrFFo="
            }
          },
          "eVjikyGdJ9bduwRXuTqWg5XTdzx4i7W5vwulsleOH2w=": {
            "valueMac": {
              "type": "Buffer",
              "data": "uI6JIadA/HSG1iU9Ln+1Py0nUET4O9VJB2UkQ4PRNy8="
            }
          },
          "8935ryzcxcxu7/g8rYcBQyh+dED+qj4lgGxD4DJvf48=": {
            "valueMac": {
              "type": "Buffer",
              "data": "9jUXBR361By2QfFhD8Qsyrgy6K5s0uZ/4q+KAfEioMY="
            }
          },
          "L78q+aSu5Z33w298JfyL94K16UOEoHpnpdsjDa6Ntws=": {
            "valueMac": {
              "type": "Buffer",
              "data": "6Re86yhH393+uaNyXqajX2w6jMBJy5WW6H8GvHNqql4="
            }
          },
          "RUKQsYp/UWAtY2VWjtkma9WzBLSbirnI/a5O+rB68Ys=": {
            "valueMac": {
              "type": "Buffer",
              "data": "HiykomJWPv3VeoeWzyhX5oTHWrNynkEt1BWIWAXoXgA="
            }
          },
          "wXpfFo4JmN18x7G4nSusPBlzDRURC0xonbFogiv4uug=": {
            "valueMac": {
              "type": "Buffer",
              "data": "CRRFM4DsG2ljxbZ0Do+/aLa5x/qDxF4PONzWlyuR+po="
            }
          },
          "HUI4GrjS5xk8NFoOH8R5DofkntG5nxpvSkyjziSRFJA=": {
            "valueMac": {
              "type": "Buffer",
              "data": "fw0QllHW3mWme1HE+r3ZFiFxENSmES4eTxF0mqQ1NVQ="
            }
          },
          "QbRDnNyjWORXOpZ4wZo+AM7Kii/A8aMJT3fyQxAGIow=": {
            "valueMac": {
              "type": "Buffer",
              "data": "T6v2m/R+sXu2JCopzUWH5CtcZU9lhW5ZujJ6Kyt/Gkk="
            }
          },
          "am4r8ecAfhy6vXWAub2eBBtnWIOjEdbrY8f5ScfqCsg=": {
            "valueMac": {
              "type": "Buffer",
              "data": "+C+0TGClpteSPnQskkRKhoFrfTclX+eNq56jblIhrWg="
            }
          },
          "ZNqmJlJuOECb69E4AhxZ59uIsPZW2TXQiJQzMrV8f+Y=": {
            "valueMac": {
              "type": "Buffer",
              "data": "sqxIvP62UFu/6BoT9bynKIcDAl35O+hzMbE/CVNxjCk="
            }
          },
          "1H7nrjM9t1RdiVNxnjrt/686Nh3Qdmlmyu7x51NOhu0=": {
            "valueMac": {
              "type": "Buffer",
              "data": "OnVlwBxd2naEN5Uh3oQ/PpjQyFcMZvSpBGlXFVSACHw="
            }
          },
          "CzBoE5Oz9l9pTK0fGTfva34Nlf0ypKQPMinrYD++Neo=": {
            "valueMac": {
              "type": "Buffer",
              "data": "5UH0zXH5281gFs7iImcOAROEzbM1jCgSUrAnTupwHEc="
            }
          },
          "JZxn9rAuHG4eKAb7h1pjf/50VcN2roaAE0fe5f2kM9k=": {
            "valueMac": {
              "type": "Buffer",
              "data": "qkLdzfVd/pBFndtSjna69J+5WdNeq2NPEUDkIXj/Nkk="
            }
          },
          "u1h6nl/WG+xLC4Pn2fi97tWuvnE71UNb17qOVMFpnpE=": {
            "valueMac": {
              "type": "Buffer",
              "data": "TfRcmNs7Qi6vYU9AWsfToVy6RfVR1MtXSbmkz6ns3yA="
            }
          },
          "eOiGRnxdRLktkJDTP+VuiWmZSlML2Tqgv5J4wIhYBio=": {
            "valueMac": {
              "type": "Buffer",
              "data": "b1mfxo7YNXFMnshylNFU5zIE3V9BG39RoufNuk5Hrl0="
            }
          },
          "WLzXx7UVB4653bJQxKbxZz2Gs8siNfZ+6zigSPH2+EQ=": {
            "valueMac": {
              "type": "Buffer",
              "data": "nFFOUvV1tf+cYLGBpTmAswgHPCNo8eU+9PonOko+T+8="
            }
          },
          "Wb3VIcDTdIsR0pwRjAq5UrtMiajFmsDoU6yhPO+YLmQ=": {
            "valueMac": {
              "type": "Buffer",
              "data": "GxBhRFHxUNugvHhVO80wR/KQ/5Po61k7GeZ+BrA0x+A="
            }
          },
          "KyeVyNIhbsNVSg/1x3Vrj3rfeCVwTq6q8mLtjNoFB2I=": {
            "valueMac": {
              "type": "Buffer",
              "data": "DQuP+7oGFPZaPd/jtB8zbiDV5jK+BXnuug3valiHLQg="
            }
          },
          "b8CKMI8xKAp9BKcLDxEcMhoVjVp9kazdKFUEgapFiDw=": {
            "valueMac": {
              "type": "Buffer",
              "data": "XGTJpWQ4cN07Ku6OPzZ2d4BKgyYnZAZlBZwSnoyhAok="
            }
          },
          "U3aWy9nR/LNUvEPprRAs//su1ijOmxqJLB+C3yR4ow0=": {
            "valueMac": {
              "type": "Buffer",
              "data": "KDc0/54rdyCjatsbzl2g7XbEnC+M5lcyJuMkoOty0AA="
            }
          },
          "MTqF609v1yQhJjHvNg2tgdSkc3z3/p5guK4Dvk4qnYU=": {
            "valueMac": {
              "type": "Buffer",
              "data": "27GmlEl+4XcepgiAoNofYj1iZLmHzSQTB5Piksj3nPo="
            }
          },
          "bQCeDt3UScttHXbUTVgKerey4j6a7kdSjxNaK8+URMM=": {
            "valueMac": {
              "type": "Buffer",
              "data": "+002piDoGY+1dyPutlluQr73U8IcYrc/+8yaIdk5KUU="
            }
          },
          "lqWEz6Jl02OKIrciRa1tVI4dmsQ2ExETD3Un3OiwTAI=": {
            "valueMac": {
              "type": "Buffer",
              "data": "LvfGDXkgaRomq3rdTl6FwlDhUq9kNQb9QG36pzdF6O4="
            }
          },
          "xQL4MbsCMff+Gyf7f4uac92ZVW0mpQe4am64R+3KdnY=": {
            "valueMac": {
              "type": "Buffer",
              "data": "ww89UxTCd54Qe0ogEYlv1+KbHYtKw37suQiZdrqAwT4="
            }
          },
          "gRWZLRivdHYBl4yU+G2ePFQkY/zbcqtV63Be70W8YC4=": {
            "valueMac": {
              "type": "Buffer",
              "data": "fsvRNz+qNeoaKGlFfLaR/cTLQFL1dwu1/Fh4Y/6M5/c="
            }
          },
          "zXYzXq6T5Xti77rQgWEfewZwsxOY7dlnqsXQ/QClmvE=": {
            "valueMac": {
              "type": "Buffer",
              "data": "fg77u4W01LSItA46Txi7Q+6s5excNz3IOsu4y1xhluU="
            }
          },
          "amO/XoJMSeFgjNdCsruE6cRR7W/IHJ5ZlNWCM6GIfGA=": {
            "valueMac": {
              "type": "Buffer",
              "data": "Yr5TweUogbxQxOx5h62iaDueImvprwhFjAjo6SqD6F4="
            }
          },
          "oW0DOCAyWSoR8bFRUKZNFSe16xFq6dqY1FPVk1bCw2w=": {
            "valueMac": {
              "type": "Buffer",
              "data": "fkPSSqHP9Ruc7K0ObeaQToNd6lunwmmZ7DJ1SCCYzS8="
            }
          },
          "yXdRs9qEKfwyDG2LpelEb8Er6+aWlRnkse+aMKSCrtY=": {
            "valueMac": {
              "type": "Buffer",
              "data": "ObJsWhYbpNiBeFerQinQ0LuRbuAr0HHIJwYkVksBG24="
            }
          },
          "PGvN8k4jbM+59bsGsHk8O4p8RVGA08x+O5duGT9KYiM=": {
            "valueMac": {
              "type": "Buffer",
              "data": "NqOlmXD65HRhenibBCZ2ZQnbgc6PI34ghEKd+jqD8oo="
            }
          },
          "3fRE9XOGsVbxNQTE+noPOg9hoUcenjy14YbQqvfoDSc=": {
            "valueMac": {
              "type": "Buffer",
              "data": "MaFvEUwtfhzCyVKkNJRWT7pdQMpZdpsGC49UXY1pq1g="
            }
          },
          "v9H6kCQUYSPRLvV9UpGJJCe1XOmsRkDPpqsjdY3RX3Q=": {
            "valueMac": {
              "type": "Buffer",
              "data": "B9nhxBvD/iwGOc44Q/Bk5cUByC9lTk5/w9wDqY1TVPg="
            }
          },
          "j+LehImet4v4gQ8XLIwJNJ9pDFixDWnon8puWFH/ahQ=": {
            "valueMac": {
              "type": "Buffer",
              "data": "BMrax2ObIWOVt6YBobbZN2DYBPooVoTUsyNPvdHPwbE="
            }
          },
          "yAQUP/AYpI7j7xCQA/5Z7XMMp5bdkgBvdy6zrUDC7tU=": {
            "valueMac": {
              "type": "Buffer",
              "data": "efQDvYtGZvYpBrE3gU36Ckf37+HL6M5q4z+H17q6eN8="
            }
          },
          "+9Ac6FYcNwOVkRZ+kbjigMpc0xLn1nONRdl979Mk0fs=": {
            "valueMac": {
              "type": "Buffer",
              "data": "Qd7+zW/BlZrPfQ9RhSwCsX3Axo/iCzq1kGVFoiVH0mw="
            }
          },
          "zoC8aO1dsOYmyiV5cqVqHfYWeFdw3LTKxIOQmFdmfR4=": {
            "valueMac": {
              "type": "Buffer",
              "data": "UvaKOn6+yWYA1mbsz8ht1xWfPUmp3ytfsFN1fJzGDdQ="
            }
          },
          "f2OqwQmD/mu0wL+5eRLds4avzh7kf5PeV82sBKO9NLk=": {
            "valueMac": {
              "type": "Buffer",
              "data": "0Lzci1bhf3UuXRxfzHKSJ4gd5o3N/3c20xWQUjR4jGs="
            }
          },
          "LApR87OgvbQ5158SB7MZpYD8niew/ZGVV9eAgpFE3ws=": {
            "valueMac": {
              "type": "Buffer",
              "data": "lmTPnZ7tASdxOYheFxAE6fhSCHj9dUZkCNMLENyZiA8="
            }
          },
          "VSgwwspianwGlIp352Nm9pYJ8Ga3ztpAwmIuBE/PlVA=": {
            "valueMac": {
              "type": "Buffer",
              "data": "9KnrLvfEpMoaGAw0Cp0q6eNdsch95OK6PIrujmaPzng="
            }
          },
          "4eKJSKjNlFIb9KAHdvF9pFl1yIL2LP+8b79S22qwTOs=": {
            "valueMac": {
              "type": "Buffer",
              "data": "Ei3W4m+SVXazk6VOr8DBlOINVr7qO5hVQVwuBZsmJPM="
            }
          },
          "LfaWMSMAlIWL/4jmvYQ6C8h8qpVGIrmx4dxrXAgNOVU=": {
            "valueMac": {
              "type": "Buffer",
              "data": "XjKBBsPlyPzN+55zMNItvj/RxV2X0LPIwzVKKECO3LM="
            }
          },
          "UjzEYh3WVJU9Ld4+ADAdMWdDei9juiq2SyeS3iokz+E=": {
            "valueMac": {
              "type": "Buffer",
              "data": "11RSyQQ1CmD6AQ4QTbba5uBTpbrwoDaBkx8lkVBfPGI="
            }
          },
          "liveqH1k5/E4XHrkfpepisbGjAGwh/xiMv8WhUyDXyE=": {
            "valueMac": {
              "type": "Buffer",
              "data": "V9EDsuagYQUApUFwOwlYC4xvutDz+rZemMWe3tNPDzE="
            }
          },
          "gPC2iyzje+ip+NVfE2lO8BijyuqJDHx5yrJPFwuORC8=": {
            "valueMac": {
              "type": "Buffer",
              "data": "jlRQ8WKwWYCG6R2pEj3KBGmHQFl0b2iec6fueSWjUGU="
            }
          },
          "vXujrzzLm3ZF5KuGOAgwT3rImpVUTyX3TJn06fYSkp8=": {
            "valueMac": {
              "type": "Buffer",
              "data": "xI+JunmX7+6y+3F2uO6ZsZWIrim4st54AzJKV1xrSks="
            }
          },
          "iZEQA0gm8F9eDUjATZod3zGeG8uO23U6zbIhPvGIjtA=": {
            "valueMac": {
              "type": "Buffer",
              "data": "zGiiemRVRm+McDBOtNRmPyAPYZ3usRXm7UQ582pxME8="
            }
          },
          "3/7a0v+eConmyDMZ8CF6afmkYLG5tNU9ywYlFWxlJLU=": {
            "valueMac": {
              "type": "Buffer",
              "data": "bmv6M8c9/rPe0ydNE15IA9pZoUa4gXIJOIwWLedxhDA="
            }
          },
          "nz93vDmmrAKX1igMciAkJjS7beMfPbrtrLfxK4tWuKk=": {
            "valueMac": {
              "type": "Buffer",
              "data": "Fzr4jB/8ue4gB+7TTI8a1UmdycSWwOkqeaGjg34inWs="
            }
          },
          "Vs4ZZmLfe7+DsR+Gqw6Fge0TdsC7neyADr4Yn/vn6d8=": {
            "valueMac": {
              "type": "Buffer",
              "data": "W7YzJ02Ib3Q7hIy+AlDooSxjPyBO+YndSzhTOY6XIpw="
            }
          },
          "r2PfqDm+Gagqi85HV5jARlEqiX1ZiD87CkagEGWNeWo=": {
            "valueMac": {
              "type": "Buffer",
              "data": "BLCI5/JhD5D8rKl+afAJLNVVsdxT6auro2u26NkU/N0="
            }
          },
          "kPvZu4TrvGu2MoutayTmx+3Om3gm6WlZVgpo0lA3JrE=": {
            "valueMac": {
              "type": "Buffer",
              "data": "B06Cgl58S2/07YsNN2QMGl6qxobv97Belw74FxbVTBM="
            }
          },
          "FDIhPHnkqccVhbw9soE0GiX2jbtXcnTPI9a0tYDxGDY=": {
            "valueMac": {
              "type": "Buffer",
              "data": "g7OIiD2NZd4dXaPPNvKlLPbAXNhuCI68Mx0eKNu34Fc="
            }
          },
          "r+E5y3Jj3ALCdLvuz2qu1ZkM+CQQlxOZiYDOCqne6c8=": {
            "valueMac": {
              "type": "Buffer",
              "data": "ESKgA0PZuF6HzZu+wnjAjUkrjs6+cuBpwKHm0Jrcr8U="
            }
          },
          "RHMkRVpdNuOrXu/rD9ynOyX6IBB4WP2mZCwoKzPYUZY=": {
            "valueMac": {
              "type": "Buffer",
              "data": "/Af5GX6d2HUhEVRySBvBReSjAJ2xC1nZt7iEbRNknTg="
            }
          },
          "aAULneWYj3xap9iqbDFd6HgQOLZu/a1TARvYRfjjni0=": {
            "valueMac": {
              "type": "Buffer",
              "data": "AmjdYq37bE8gonnRW1asKqoilI3jFzpYab5oPkZSS9g="
            }
          },
          "HBLHpJeeaPj8Bm/aK062dZuv4ur9qTrEjN7uUVTkXpQ=": {
            "valueMac": {
              "type": "Buffer",
              "data": "ucbC+xPJobmPk7sSblh46Q6NdJyV9hMuvGV22HCJSZs="
            }
          },
          "aoJLzrT5RxZ/jRZPuWehSHXS6VOwEemALXozTGNJGOo=": {
            "valueMac": {
              "type": "Buffer",
              "data": "3C/itQt2qhuI9PtTa6ECXIWQzWuu3bpMz09kcUys0ZY="
            }
          },
          "5+NdJGO1o0mkzyJ5cEesrPEpHtmgamQe7sPqKufOLTo=": {
            "valueMac": {
              "type": "Buffer",
              "data": "6g+cBbdDxFUQNvvsWFUz3UCWn9geVqbcYSMQVKHHAKw="
            }
          },
          "Up7FWzahoKEbt5oZCJ5T9Beyt1h3ennDcsmdk84X140=": {
            "valueMac": {
              "type": "Buffer",
              "data": "/NSb5PFmAjKnxjO2GGw7ZaFy0+TkBph+egOht3eopFU="
            }
          },
          "bXRD1ckoSoRZkqHckuhwYw9tZZU9/hWdsjOlrySfz9w=": {
            "valueMac": {
              "type": "Buffer",
              "data": "OxDllahI9zntSH4+RvJ2FWJiTsi+OdcE9j7EERd+tlo="
            }
          },
          "lEh7JkZvKnLdBh2uik7pKcMyrXwK4MoVUAV/IEiWsGE=": {
            "valueMac": {
              "type": "Buffer",
              "data": "IGmUQF8o/so55Nu/UFIwFjUuO7TUYEwkLeWsHfrJpFA="
            }
          },
          "+HrCle3/G2YkbtvXXXlL0jPKs5hAjXzrC5whVVixo+k=": {
            "valueMac": {
              "type": "Buffer",
              "data": "fesTv7gMwJNCHulMwMt6RkODMUZqncOS1/R/tXqo26g="
            }
          },
          "R4enlvBnQxvxbUz85VcLF8Efd+xJJzg02F3+7Jh7K8w=": {
            "valueMac": {
              "type": "Buffer",
              "data": "unwfe0pRTF6bPdt/UKMHTEuD6YJqaYRxXALd1Q6aKH0="
            }
          },
          "u00iHfkCt0Ihdg0ccSNMn6I0PnNBC3DCc2t+8c2m2V8=": {
            "valueMac": {
              "type": "Buffer",
              "data": "SZ2dsG/lvmL6IawMac/lK+qWqMKj4LhCwEocWAjSZ4s="
            }
          },
          "b8XBb5uceaIhgp7KXagrE268kK6ku+eF7KsvbH3ILHQ=": {
            "valueMac": {
              "type": "Buffer",
              "data": "GG7/OHBbEQbJw8wrzLk3WsiI53h37yRBzRtP+89Se70="
            }
          },
          "E3YimaVMoxh20t6CL4SO/kk7LhXDA6tdDm5qOZSNS8E=": {
            "valueMac": {
              "type": "Buffer",
              "data": "A2GqWo/+kneqM9OVz1x2KanOp0E+Yi2H0OXJvgp3M+s="
            }
          },
          "Sant45RUUI+/HOOgrgoWZ9e5cMyEhypPzA5BSls41gk=": {
            "valueMac": {
              "type": "Buffer",
              "data": "a+3IbtvIasguY1RiLZvHABdFpJOyimwkgLPKhK5EQU4="
            }
          },
          "/txDKnYGc6wYw1C6QLcZWpsHWIN0T7yS7SifdAcVqgM=": {
            "valueMac": {
              "type": "Buffer",
              "data": "d4eRiQF8h7Ez1FnC2qAJpTxABcLThS/N3dfD23IwIZ0="
            }
          },
          "rwBJz3/wCB9856S0SwDwxJUUDDxvwa9jZKrvFEP8SlI=": {
            "valueMac": {
              "type": "Buffer",
              "data": "CmwtVJAnZisAWt5ZeOXoN5w3G5KwntGul0OwQO2xqdI="
            }
          },
          "ReXy2ERf0Te7aCLY/21maib9tFbH9tLqdarqnL9nTEE=": {
            "valueMac": {
              "type": "Buffer",
              "data": "EF0YuvQIO7hTF1IcPJ7VMeyS20k58FLf2x/kylzibFA="
            }
          },
          "a9lMDykiHfgquCuc5XxeJeztwEYsRVdSguwYyhjUJaU=": {
            "valueMac": {
              "type": "Buffer",
              "data": "PJ9yYK8d26yHnJHCQfa1Atgssur7aSjxmB8TcIAZRHA="
            }
          },
          "Pl7lDk8AIbnMMkA1dn+hmTsEu6UngsJ6bJjSUM95rCg=": {
            "valueMac": {
              "type": "Buffer",
              "data": "fqMAq+GbF4aWjmjKsD3kRPxS/z8fk4HPKPJ9OhxL2Aw="
            }
          },
          "6dmNmM3z1emuMJ2pIthEuuYM2PTkUeMKhUNk6Khloak=": {
            "valueMac": {
              "type": "Buffer",
              "data": "BKiwv9dSwPn5XeFWBbiXFOaVXY/05n7nS7xB6O3yrXY="
            }
          },
          "3sZvjqvHZwdr3j3xF6QxkRa8MLVtwj6kEoZiWgXc7ZA=": {
            "valueMac": {
              "type": "Buffer",
              "data": "A/+2/v1bzmN5HLZfSM+mugDP5/HgKMKpYQiCF3UGdcM="
            }
          },
          "9C4HagJs/p/CvSdr78xnS9Ao0p+1qsgZEz10bjtuQus=": {
            "valueMac": {
              "type": "Buffer",
              "data": "5kfPXxm/XkU4exVfEFNNU7jsFJOVhZ5rl1oj16pW1Mg="
            }
          },
          "DBsualrzFZjnrs7Bajdx5mMcQgXAGw5STDV9wMKN3o0=": {
            "valueMac": {
              "type": "Buffer",
              "data": "Ofeg7wySihv7v2EJuyNQXkDOWggblqn2NTEtqJeNze4="
            }
          },
          "cuUiRvTkhdDlRD/i4rq4vKhtmTSBjNRwYRS8HRqbJHQ=": {
            "valueMac": {
              "type": "Buffer",
              "data": "QxZdG82zrSanAIOZFXnHG/6AgQ4dYtzeAs1QA7/+R3w="
            }
          },
          "SCYVOsEuCoYmG+CT7v6vpZkG1Q02D4V8j4HTVWWRVac=": {
            "valueMac": {
              "type": "Buffer",
              "data": "o5eErn9evyq+AHCVAVH3wzSh/tSKFag5oLG31N2eSu4="
            }
          },
          "IYkF2PmD+94Ai8EWZjG2wgxMhdD9wR8/RQvt5zSmMKw=": {
            "valueMac": {
              "type": "Buffer",
              "data": "YkzpkK8eZsj66S7IObKFX4WUwujz15A/IzHtwpDYIlU="
            }
          },
          "pycStV0lFyiorFnjD+xPxN6rCBTZxlsAlYwfJi9Qetc=": {
            "valueMac": {
              "type": "Buffer",
              "data": "W2xShVF90vGwaxiaW9okXnr5sZbLy6Xxurr2i6KmzgI="
            }
          }
        }
      },
      "regular_low": {
        "version": 1,
        "hash": {
          "type": "Buffer",
          "data": "KMEYoliii9VkQSNlaKI583M51qliymOT66msv/xrr/qiZzs8SCheVTkszy1vnV9NvON9sODr6C55wyd/gMzKvwcCdik5n9c0OayyvKh7FDVfIHjqbqZNL2dKEjeOZJZkQaNyNLWIXbnACW+xjJmmoToO0Q6G2geljM/UZlM0YjU="
        },
        "indexValueMap": {
          "jE9X79+8c7HXoe/FFcFKlqNwICv7Ri+W/LRxmhNMQQg=": {
            "valueMac": {
              "type": "Buffer",
              "data": "8VDczt40zIx3ZoUKyC5/rQwAvYw3mu7fLoBgo5RpHZo="
            }
          }
        }
      }
    },
    "senderKeys": {
      "120363045959225925@g.us::6285783926465::0": [
        {
          "senderKeyId": 1970656213,
          "senderChainKey": {
            "iteration": 6,
            "seed": "R8/cLnrMZb0O6/pPTES1RpPrQ9eD+GU/APFHczKJ16Q="
          },
          "senderSigningKey": {
            "public": "BcBKT+bfUGduUh5m3H9NfYbKd5C2sfj4GFia5IlHAEt6"
          }
        }
      ],
      "120363045959225925@g.us::6281214281312:28::0": [
        {
          "senderKeyId": 432316974,
          "senderChainKey": {
            "iteration": 4,
            "seed": "NC1/mYmmn7i4jcIYSQyPGv184LPNzucUKVwFwSkS6XU="
          },
          "senderSigningKey": {
            "public": "BTmIw7kkb/tWnTTGzBwFOrESL+EO252F1Y73+gdqJ9xU"
          }
        },
        {
          "senderKeyId": 432316974,
          "senderChainKey": {
            "iteration": 2,
            "seed": "sfQVJ8YxKTKEQG8cGEVbGfmoHyb95LyxVMDVgOE/CxA="
          },
          "senderSigningKey": {
            "public": "BTmIw7kkb/tWnTTGzBwFOrESL+EO252F1Y73+gdqJ9xU"
          }
        },
        {
          "senderKeyId": 432316974,
          "senderChainKey": {
            "iteration": 3,
            "seed": "6BxUxp73lCy94i6qaZcRkS0/VeOqFmaYyniXBdeQn0s="
          },
          "senderSigningKey": {
            "public": "BTmIw7kkb/tWnTTGzBwFOrESL+EO252F1Y73+gdqJ9xU"
          }
        }
      ]
    }
  }
}
